LICENSE
README.md
setup.py
fermi_stacking/__init__.py
fermi_stacking/client.py
fermi_stacking/make_new_run.py
fermi_stacking/submit_fermi_stacking_jobs.py
fermi_stacking.egg-info/PKG-INFO
fermi_stacking.egg-info/SOURCES.txt
fermi_stacking.egg-info/dependency_links.txt
fermi_stacking.egg-info/entry_points.txt
fermi_stacking.egg-info/requires.txt
fermi_stacking.egg-info/top_level.txt
fermi_stacking/analyze_results/AnalyzeResults.py
fermi_stacking/analyze_results/__init__.py
fermi_stacking/pop_studies/PopStudies.py
fermi_stacking/pop_studies/__init__.py
fermi_stacking/preprocessing/Preprocess.py
fermi_stacking/preprocessing/__init__.py
fermi_stacking/science_tools/BinnedAnalysis.py
fermi_stacking/science_tools/__init__.py
fermi_stacking/stacking/AlphaBeta.py
fermi_stacking/stacking/Stack.py
fermi_stacking/stacking/__init__.py