Metadata-Version: 2.1
Name: fermi_stacking
Version: 0.1.5a0
Summary: Performs Fermi-LAT stacking analysis.
Home-page: https://github.com/ckarwin/Fermi_Stacking_Analysis.git
Author: Chris Karwin
Author-email: christopher.m.karwin@nasa.gov
License-File: LICENSE
Requires-Dist: pandas
Requires-Dist: pyyaml
